gifnoc/__init__.py
gifnoc/__main__.py
gifnoc/proxy.py
gifnoc/py.typed
gifnoc/registry.py
gifnoc/version.py
gifnoc/std/__init__.py
gifnoc/std/_random.py
gifnoc/std/_time.py
gifnoc-0.6.3.dist-info/METADATA
gifnoc-0.6.3.dist-info/WHEEL
gifnoc-0.6.3.dist-info/entry_points.txt
gifnoc-0.6.3.dist-info/RECORD
