Metadata-Version: 2.4
Name: gifnoc
Version: 0.6.3
Summary: Handle configuration for multiple libraries
Project-URL: Homepage, https://github.com/breuleux/gifnoc
Project-URL: Repository, https://github.com/breuleux/gifnoc
Author-email: Olivier Breuleux <breuleux@gmail.com>
License-Expression: MIT
Requires-Python: >=3.11
Requires-Dist: cryptography>=45.0.7
Requires-Dist: ovld<0.6.0,>=0.5.13
Requires-Dist: pyyaml>=6.0.2
Requires-Dist: serieux<0.4.0,>=0.3.0
